{"queryId":"5a3abdb4-2201-489f-ad9e-b7c2790806e6","formattedDate":"20-10-2021 12:54:17","segments":[{"segment_id":"v_05981_385","global":{"features_AverageFuzzyHist":0.0},"local":{},"value":null},{"segment_id":"v_02611_33","global":{"features_AverageFuzzyHistNormalized":0.0,"features_AverageFuzzyHist":0.0},"local":{"features_AverageColorRaster":0.73828125},"value":null},{"segment_id":"v_05981_384","global":{"features_AverageFuzzyHist":0.0},"local":{},"value":null},{"segment_id":"v_02611_32","global":{"features_AverageFuzzyHistNormalized":0.0,"features_AverageFuzzyHist":0.0},"local":{},"value":null},{"segment_id":"v_05981_383","global":{"features_AverageFuzzyHist":0.0},"local":{},"value":null},{"segment_id":"v_05981_382","global":{"features_AverageFuzzyHist":0.0},"local":{},"value":null},{"segment_id":"v_05981_381","global":{"features_AverageFuzzyHist":0.0},"local":{},"value":null},{"segment_id":"v_05981_380","global":{"features_AverageFuzzyHist":0.0},"local":{},"value":null},{"segment_id":"v_05981_379","global":{"features_AverageFuzzyHist":0.0},"local":{"features_AverageColorRaster":0.7488281250000001},"value":0.09360351562500001},{"segment_id":"v_05981_378","global":{"features_AverageFuzzyHist":0.0},"local":{},"value":null},{"segment_id":"v_05981_377","global":{"features_AverageFuzzyHist":0.0},"local":{},"value":null},{"segment_id":"v_05981_376","global":{"features_AverageFuzzyHist":0.0},"local":{},"value":null},{"segment_id":"v_05981_375","global":{"features_AverageFuzzyHist":0.0},"local":{},"value":null},{"segment_id":"v_04254_941","global":{"features_MedianFuzzyHist":0.0,"features_AverageFuzzyHistNormalized":0.0,"features_AverageFuzzyHist":0.0},"local":{},"value":null},{"segment_id":"v_05981_374","global":{"features_AverageFuzzyHist":0.0},"local":{},"value":null},{"segment_id":"v_04254_940","global":{"features_MedianFuzzyHist":0.0,"features_AverageFuzzyHistNormalized":0.0,"features_AverageFuzzyHist":0.0},"local":{},"value":null},{"segment_id":"v_05981_373","global":{"features_AverageFuzzyHist":0.0},"local":{},"value":null},{"segment_id":"v_05981_372","global":{"features_AverageFuzzyHist":0.0},"local":{},"value":null},{"segment_id":"v_04254_939","global":{"features_MedianFuzzyHist":0.0,"features_AverageFuzzyHistNormalized":0.0,"features_AverageFuzzyHist":0.0},"local":{},"value":null},{"segment_id":"v_05981_371","global":{"features_AverageFuzzyHist":0.0},"local":{},"value":null},{"segment_id":"v_05981_370","global":{"features_AverageFuzzyHist":0.0},"local":{},"value":null},{"segment_id":"v_05981_369","global":{"features_AverageFuzzyHist":0.0},"local":{},"value":null},{"segment_id":"v_04254_938","global":{"features_MedianFuzzyHist":0.0,"features_AverageFuzzyHistNormalized":0.0,"features_AverageFuzzyHist":0.0},"local":{},"value":null},{"segment_id":"v_02611_31","global":{"features_AverageFuzzyHistNormalized":0.0,"features_AverageFuzzyHist":0.0},"local":{},"value":null},{"segment_id":"v_05981_368","global":{"features_AverageFuzzyHist":0.0},"local":{},"value":null},{"segment_id":"v_02611_30","global":{"features_AverageFuzzyHistNormalized":0.0,"features_AverageFuzzyHist":0.0},"local":{"features_AverageColorRaster":0.8015625000000001},"value":0.10019531250000001},{"segment_id":"v_04254_937","global":{"features_MedianFuzzyHist":0.0,"features_AverageFuzzyHistNormalized":0.0,"features_AverageFuzzyHist":0.0},"local":{},"value":null},{"segment_id":"v_05981_367","global":{"features_AverageFuzzyHist":0.0},"local":{},"value":null},{"segment_id":"v_02611_29","global":{"features_AverageFuzzyHistNormalized":0.0,"features_AverageFuzzyHist":0.0},"local":{},"value":null},{"segment_id":"v_04254_936","global":{"features_MedianFuzzyHist":0.0,"features_AverageFuzzyHistNormalized":0.0,"features_AverageFuzzyHist":0.0},"local":{},"value":null},{"segment_id":"v_05981_366","global":{"features_AverageFuzzyHist":0.0},"local":{},"value":null},{"segment_id":"v_02611_28","global":{"features_AverageFuzzyHistNormalized":0.0,"features_AverageFuzzyHist":0.0},"local":{"features_AverageColorRaster":0.8015625000000001},"value":0.10019531250000001},{"segment_id":"v_04254_935","global":{"features_MedianFuzzyHist":0.0,"features_AverageFuzzyHistNormalized":0.0,"features_AverageFuzzyHist":0.0},"local":{},"value":null},{"segment_id":"v_02611_27","global":{"features_AverageFuzzyHistNormalized":0.0,"features_AverageFuzzyHist":0.0},"local":{},"value":null},{"segment_id":"v_05981_365","global":{"features_AverageFuzzyHist":0.0},"local":{},"value":null},{"segment_id":"v_04254_934","global":{"features_MedianFuzzyHist":0.0,"features_AverageFuzzyHistNormalized":0.0,"features_AverageFuzzyHist":0.0},"local":{},"value":null},{"segment_id":"v_02611_26","global":{"features_AverageFuzzyHistNormalized":0.0,"features_AverageFuzzyHist":0.0},"local":{},"value":null},{"segment_id":"v_05981_364","global":{"features_AverageFuzzyHist":0.0},"local":{},"value":null},{"segment_id":"v_04254_933","global":{"features_MedianFuzzyHist":0.0,"features_AverageFuzzyHistNormalized":0.0,"features_AverageFuzzyHist":0.0},"local":{},"value":null},{"segment_id":"v_05981_363","global":{"features_AverageFuzzyHist":0.0},"local":{},"value":null},{"segment_id":"v_02611_25","global":{"features_AverageFuzzyHistNormalized":0.0,"features_AverageFuzzyHist":0.0},"local":{},"value":null},{"segment_id":"v_04254_932","global":{"features_MedianFuzzyHist":0.0,"features_AverageFuzzyHistNormalized":0.0,"features_AverageFuzzyHist":0.0},"local":{},"value":null},{"segment_id":"v_05981_362","global":{"features_AverageFuzzyHist":0.0},"local":{},"value":null},{"segment_id":"v_04254_931","global":{"features_MedianFuzzyHist":0.0,"features_AverageFuzzyHistNormalized":0.0,"features_AverageFuzzyHist":0.0},"local":{},"value":null},{"segment_id":"v_04254_930","global":{"features_MedianFuzzyHist":0.0,"features_AverageFuzzyHistNormalized":0.0,"features_AverageFuzzyHist":0.0},"local":{},"value":null},{"segment_id":"v_04254_929","global":{"features_MedianFuzzyHist":0.0,"features_AverageFuzzyHistNormalized":0.0,"features_AverageFuzzyHist":0.0},"local":{},"value":null},{"segment_id":"v_04254_928","global":{"features_MedianFuzzyHist":0.0,"features_AverageFuzzyHistNormalized":0.0,"features_AverageFuzzyHist":0.0},"local":{},"value":null},{"segment_id":"v_04254_927","global":{"features_MedianFuzzyHist":0.0,"features_AverageFuzzyHistNormalized":0.0,"features_AverageFuzzyHist":0.0},"local":{},"value":null},{"segment_id":"v_04254_926","global":{"features_MedianFuzzyHist":0.0,"features_AverageFuzzyHistNormalized":0.0,"features_AverageFuzzyHist":0.0},"local":{},"value":null},{"segment_id":"v_05981_361","global":{"features_AverageFuzzyHist":0.0},"local":{},"value":null}]}