{"queryId":"c34dfed6-a9df-467a-872b-1586558262cb","formattedDate":"10-10-2021 19:37:08","segments":[{"segment_id":"v_04889_61","global":{"features_AverageColor":2.2210395044210003,"features_MedianColor":1.1200357047878966},"local":{},"value":1.077766196518999},{"segment_id":"v_04889_62","global":{"features_AverageColor":2.2625875385440124,"features_MedianColor":1.0685158281910174},"local":{},"value":0.5372747365701661},{"segment_id":"v_00353_102","global":{"features_AverageColor":2.2111774021265456,"features_MedianColor":0.9983524867466518},"local":{},"value":0.5176661111085803},{"segment_id":"v_00368_110","global":{"features_AverageColor":2.1582376414415787,"features_MedianColor":0.9957486288888114},"local":{},"value":0.5087074629565146},{"segment_id":"v_01278_123","global":{"features_MedianColor":1.084901560569296},"local":{"features_AverageColorGrid8":0.9660213484580481},"value":0.2648465736918204},{"segment_id":"v_06707_220","global":{"features_MedianColor":1.067685267390037},"local":{"features_AverageColorGrid8":0.9773060787097951},"value":0.2631194945602945},{"segment_id":"v_05277_159","global":{"features_MedianColor":1.0410216779124981},"local":{"features_AverageColorGrid8":0.9883655045287106},"value":0.2598476994094128},{"segment_id":"v_02091_145","global":{"features_MedianColor":1.045825142763099},"local":{"features_AverageColorGrid8":0.9616404039777429},"value":0.2581363959394647},{"segment_id":"v_05221_162","global":{"features_MedianColor":1.0037073407854353},"local":{"features_AverageColorGrid8":1.021032810871589},"value":0.2568680771319922},{"segment_id":"v_05580_163","global":{"features_MedianColor":1.0251454061391403},"local":{"features_AverageColorGrid8":0.9703640779998387},"value":0.25561245910869856},{"segment_id":"v_03662_91","global":{"features_MedianColor":0.9972009250095912},"local":{"features_AverageColorGrid8":0.9782791677170587},"value":0.2518415721485202},{"segment_id":"v_04039_2","global":{"features_MedianColor":1.0312158253728125},"local":{"features_CLD":0.7826530612244899},"value":0.23913006905250672},{"segment_id":"v_02630_18","global":{"features_AverageFuzzyHist":0.0,"features_MedianColor":1.1211083198080256},"local":{"features_AverageColorRaster":0.57421875},"value":0.2342396202241002},{"segment_id":"v_03998_1","global":{"features_MedianColor":1.001759789914501},"local":{"features_CLD":0.7693877551020408},"value":0.23314511362660975},{"segment_id":"v_02630_16","global":{"features_AverageFuzzyHist":0.0,"features_MedianColor":1.1016811799029915},"local":{"features_AverageColorRaster":0.57421875},"value":0.23110621056199793},{"segment_id":"v_00353_200","global":{"features_MedianColor":1.0324500531566387},"local":{"features_CLD":0.6606122448979592},"value":0.2279765039730115},{"segment_id":"v_02941_27","global":{"features_MedianColor":0.9986299475845025},"local":{"features_CLD":0.676530612244898},"value":0.2240024265934249},{"segment_id":"v_04261_53","global":{"features_MedianColor":1.0199087648975604},"local":{"features_AverageColorRaster":0.63671875},"value":0.22373106485594563},{"segment_id":"v_00080_38","global":{"features_MedianFuzzyHist":0.0,"features_AverageFuzzyHist":0.0,"features_MedianColor":1.0311433363933953},"local":{"features_AverageColorRaster":0.55859375},"value":0.21827565065609905},{"segment_id":"v_05941_248","global":{"features_MedianColor":1.0129216622333137},"local":{"features_AverageColorRaster":0.5625},"value":0.21570004304588333},{"segment_id":"v_00091_74","global":{"features_MedianFuzzyHist":0.0,"features_MedianColor":1.0036895090219924},"local":{"features_AverageColorRaster":0.5625},"value":0.2142109860763154},{"segment_id":"v_02494_26","global":{"features_MedianColor":1.1719589856206154},"local":{},"value":0.18902564284203477},{"segment_id":"v_06271_58","global":{"features_MedianColor":1.1719589856206154},"local":{},"value":0.18902564284203477},{"segment_id":"v_02397_28","global":{"features_MedianColor":1.1718607649511221},"local":{},"value":0.1890098007985681},{"segment_id":"v_00807_48","global":{"features_MedianColor":1.1718607649511221},"local":{},"value":0.1890098007985681},{"segment_id":"v_04351_97","global":{"features_MedianColor":1.1702699427701988},"local":{},"value":0.18875321657583854},{"segment_id":"v_07113_93","global":{"features_MedianColor":1.1702699427701988},"local":{},"value":0.18875321657583854},{"segment_id":"v_00099_368","global":{"features_MedianColor":1.1702128857982401},"local":{},"value":0.18874401383842584},{"segment_id":"v_00438_27","global":{"features_MedianColor":1.1702128857982401},"local":{},"value":0.18874401383842584},{"segment_id":"v_06229_2","global":{"features_MedianColor":1.164059724613112},"local":{},"value":0.18775156848598581},{"segment_id":"v_06820_119","global":{"features_MedianColor":1.164059724613112},"local":{},"value":0.18775156848598581},{"segment_id":"v_01612_47","global":{"features_MedianColor":1.164059724613112},"local":{},"value":0.18775156848598581},{"segment_id":"v_04810_101","global":{"features_MedianColor":1.164059724613112},"local":{},"value":0.18775156848598581},{"segment_id":"v_06046_98","global":{"features_MedianColor":1.164059724613112},"local":{},"value":0.18775156848598581},{"segment_id":"v_04827_36","global":{"features_MedianColor":1.164059724613112},"local":{},"value":0.18775156848598581},{"segment_id":"v_06623_17","global":{"features_MedianColor":1.164059724613112},"local":{},"value":0.18775156848598581},{"segment_id":"v_03174_124","global":{"features_MedianColor":1.164059724613112},"local":{},"value":0.18775156848598581},{"segment_id":"v_06156_183","global":{"features_MedianColor":1.164059724613112},"local":{},"value":0.18775156848598581},{"segment_id":"v_07387_8","global":{"features_MedianColor":1.164059724613112},"local":{},"value":0.18775156848598581},{"segment_id":"v_03853_25","global":{"features_MedianColor":1.1639445713588168},"local":{},"value":0.18773299538045435},{"segment_id":"v_06527_441","global":{"features_MedianColor":1.163941698658223},"local":{},"value":0.1877325320416489},{"segment_id":"v_02371_111","global":{"features_MedianColor":1.163941698658223},"local":{},"value":0.1877325320416489},{"segment_id":"v_04573_82","global":{"features_MedianColor":1.163941698658223},"local":{},"value":0.1877325320416489},{"segment_id":"v_02970_24","global":{"features_MedianColor":1.163941698658223},"local":{},"value":0.1877325320416489},{"segment_id":"v_03187_64","global":{"features_MedianColor":1.163941698658223},"local":{},"value":0.1877325320416489},{"segment_id":"v_00849_703","global":{"features_MedianColor":1.163612920410779},"local":{},"value":0.18767950329206115},{"segment_id":"v_03332_7","global":{"features_MedianColor":1.163612920410779},"local":{},"value":0.18767950329206115},{"segment_id":"v_05207_81","global":{"features_MedianColor":1.1584616719460001},"local":{},"value":0.18684865676548393},{"segment_id":"v_06382_137","global":{"features_MedianColor":1.1584616719460001},"local":{},"value":0.18684865676548393},{"segment_id":"v_06382_138","global":{"features_MedianColor":1.1584616719460001},"local":{},"value":0.18684865676548393}]}