{"queryId":"e21634c5-e44d-4f1d-81f3-e87aa40b187e","formattedDate":"05-11-2021 12:34:03","segments":[{"segment_id":"v_02682_188","global":{"features_MedianFuzzyHist":0.0,"features_AverageFuzzyHistNormalized":0.0},"local":{"features_AverageColorRaster":0.5554687500000001},"value":0.06943359375000001},{"segment_id":"v_05981_30","global":{"features_MedianFuzzyHist":0.0,"features_AverageFuzzyHist":0.0},"local":{"features_AverageColorRaster":0.47109375000000003},"value":0.058886718750000004},{"segment_id":"v_04254_868","global":{"features_MedianFuzzyHist":0.0,"features_AverageFuzzyHistNormalized":0.0,"features_AverageFuzzyHist":0.0},"local":{},"value":null},{"segment_id":"v_05981_29","global":{"features_MedianFuzzyHist":0.0,"features_AverageFuzzyHist":0.0},"local":{},"value":null},{"segment_id":"v_02682_189","global":{"features_MedianFuzzyHist":0.0,"features_AverageFuzzyHistNormalized":0.0},"local":{"features_AverageColorRaster":0.9070312500000001},"value":0.11337890625000001},{"segment_id":"v_04254_866","global":{"features_MedianFuzzyHist":0.0,"features_AverageFuzzyHistNormalized":0.0,"features_AverageFuzzyHist":0.0},"local":{},"value":null},{"segment_id":"v_05981_28","global":{"features_MedianFuzzyHist":0.0,"features_AverageFuzzyHist":0.0},"local":{"features_AverageColorRaster":0.6785156250000001},"value":0.08481445312500001},{"segment_id":"v_05981_27","global":{"features_MedianFuzzyHist":0.0,"features_AverageFuzzyHist":0.0},"local":{"features_AverageColorRaster":0.481640625},"value":0.060205078125},{"segment_id":"v_02682_187","global":{"features_MedianFuzzyHist":0.0,"features_AverageFuzzyHistNormalized":0.0},"local":{},"value":null},{"segment_id":"v_04254_863","global":{"features_MedianFuzzyHist":0.0,"features_AverageFuzzyHistNormalized":0.0,"features_AverageFuzzyHist":0.0},"local":{},"value":null},{"segment_id":"v_05981_26","global":{"features_MedianFuzzyHist":0.0,"features_AverageFuzzyHist":0.0},"local":{},"value":null},{"segment_id":"v_02682_186","global":{"features_MedianFuzzyHist":0.0,"features_AverageFuzzyHistNormalized":0.0},"local":{},"value":null},{"segment_id":"v_04254_865","global":{"features_MedianFuzzyHist":0.0,"features_AverageFuzzyHistNormalized":0.0,"features_AverageFuzzyHist":0.0},"local":{},"value":null},{"segment_id":"v_05981_25","global":{"features_MedianFuzzyHist":0.0,"features_AverageFuzzyHist":0.0},"local":{"features_AverageColorRaster":0.5765625},"value":0.0720703125},{"segment_id":"v_04254_864","global":{"features_MedianFuzzyHist":0.0,"features_AverageFuzzyHistNormalized":0.0,"features_AverageFuzzyHist":0.0},"local":{},"value":null},{"segment_id":"v_05981_24","global":{"features_MedianFuzzyHist":0.0,"features_AverageFuzzyHist":0.0},"local":{},"value":null},{"segment_id":"v_05981_23","global":{"features_MedianFuzzyHist":0.0,"features_AverageFuzzyHist":0.0},"local":{},"value":null},{"segment_id":"v_04254_862","global":{"features_MedianFuzzyHist":0.0,"features_AverageFuzzyHistNormalized":0.0,"features_AverageFuzzyHist":0.0},"local":{},"value":null},{"segment_id":"v_05981_22","global":{"features_MedianFuzzyHist":0.0,"features_AverageFuzzyHist":0.0},"local":{"features_AverageColorRaster":0.6433593750000001},"value":0.08041992187500001},{"segment_id":"v_04254_861","global":{"features_MedianFuzzyHist":0.0,"features_AverageFuzzyHistNormalized":0.0,"features_AverageFuzzyHist":0.0},"local":{},"value":null},{"segment_id":"v_04254_860","global":{"features_MedianFuzzyHist":0.0,"features_AverageFuzzyHistNormalized":0.0,"features_AverageFuzzyHist":0.0},"local":{},"value":null},{"segment_id":"v_05981_21","global":{"features_MedianFuzzyHist":0.0,"features_AverageFuzzyHist":0.0},"local":{},"value":null},{"segment_id":"v_04254_859","global":{"features_MedianFuzzyHist":0.0,"features_AverageFuzzyHistNormalized":0.0,"features_AverageFuzzyHist":0.0},"local":{},"value":null},{"segment_id":"v_05981_20","global":{"features_MedianFuzzyHist":0.0,"features_AverageFuzzyHist":0.0},"local":{"features_AverageColorRaster":0.6328125},"value":0.0791015625},{"segment_id":"v_04254_858","global":{"features_MedianFuzzyHist":0.0,"features_AverageFuzzyHistNormalized":0.0,"features_AverageFuzzyHist":0.0},"local":{},"value":null},{"segment_id":"v_05981_18","global":{"features_MedianFuzzyHist":0.0,"features_AverageFuzzyHist":0.0},"local":{"features_AverageColorRaster":0.7453125},"value":0.0931640625},{"segment_id":"v_04254_857","global":{"features_MedianFuzzyHist":0.0,"features_AverageFuzzyHistNormalized":0.0,"features_AverageFuzzyHist":0.0},"local":{},"value":null},{"segment_id":"v_05981_19","global":{"features_MedianFuzzyHist":0.0,"features_AverageFuzzyHist":0.0},"local":{"features_AverageColorRaster":0.65390625},"value":0.08173828125},{"segment_id":"v_04254_856","global":{"features_MedianFuzzyHist":0.0,"features_AverageFuzzyHistNormalized":0.0,"features_AverageFuzzyHist":0.0},"local":{},"value":null},{"segment_id":"v_05981_17","global":{"features_MedianFuzzyHist":0.0,"features_AverageFuzzyHist":0.0},"local":{"features_AverageColorRaster":0.875390625},"value":0.109423828125},{"segment_id":"v_04254_855","global":{"features_MedianFuzzyHist":0.0,"features_AverageFuzzyHistNormalized":0.0,"features_AverageFuzzyHist":0.0},"local":{},"value":null},{"segment_id":"v_05981_16","global":{"features_MedianFuzzyHist":0.0,"features_AverageFuzzyHist":0.0},"local":{"features_AverageColorRaster":0.78046875},"value":0.09755859375},{"segment_id":"v_04254_854","global":{"features_MedianFuzzyHist":0.0,"features_AverageFuzzyHistNormalized":0.0,"features_AverageFuzzyHist":0.0},"local":{},"value":null},{"segment_id":"v_05981_15","global":{"features_MedianFuzzyHist":0.0,"features_AverageFuzzyHist":0.0},"local":{"features_AverageColorRaster":0.9140625},"value":0.1142578125},{"segment_id":"v_04254_852","global":{"features_MedianFuzzyHist":0.0,"features_AverageFuzzyHistNormalized":0.0,"features_AverageFuzzyHist":0.0},"local":{},"value":null},{"segment_id":"v_04254_853","global":{"features_MedianFuzzyHist":0.0,"features_AverageFuzzyHistNormalized":0.0,"features_AverageFuzzyHist":0.0},"local":{},"value":null},{"segment_id":"v_04254_851","global":{"features_MedianFuzzyHist":0.0,"features_AverageFuzzyHistNormalized":0.0,"features_AverageFuzzyHist":0.0},"local":{},"value":null},{"segment_id":"v_04254_850","global":{"features_MedianFuzzyHist":0.0,"features_AverageFuzzyHistNormalized":0.0,"features_AverageFuzzyHist":0.0},"local":{},"value":null},{"segment_id":"v_05981_14","global":{"features_MedianFuzzyHist":0.0,"features_AverageFuzzyHist":0.0},"local":{"features_AverageColorRaster":1.01953125},"value":0.12744140625},{"segment_id":"v_02682_185","global":{"features_MedianFuzzyHist":0.0,"features_AverageFuzzyHistNormalized":0.0},"local":{"features_AverageColorRaster":0.5027343750000001},"value":0.06284179687500001},{"segment_id":"v_04254_849","global":{"features_MedianFuzzyHist":0.0,"features_AverageFuzzyHistNormalized":0.0,"features_AverageFuzzyHist":0.0},"local":{},"value":null},{"segment_id":"v_05981_13","global":{"features_MedianFuzzyHist":0.0,"features_AverageFuzzyHist":0.0},"local":{},"value":null},{"segment_id":"v_02682_182","global":{"features_MedianFuzzyHist":0.0,"features_AverageFuzzyHistNormalized":0.0},"local":{},"value":null},{"segment_id":"v_04254_848","global":{"features_MedianFuzzyHist":0.0,"features_AverageFuzzyHistNormalized":0.0,"features_AverageFuzzyHist":0.0},"local":{},"value":null},{"segment_id":"v_05981_12","global":{"features_MedianFuzzyHist":0.0,"features_AverageFuzzyHist":0.0},"local":{"features_AverageColorRaster":0.5554687500000001},"value":0.06943359375000001},{"segment_id":"v_04254_847","global":{"features_MedianFuzzyHist":0.0,"features_AverageFuzzyHistNormalized":0.0,"features_AverageFuzzyHist":0.0},"local":{},"value":null},{"segment_id":"v_05981_11","global":{"features_MedianFuzzyHist":0.0,"features_AverageFuzzyHist":0.0},"local":{},"value":null},{"segment_id":"v_04254_846","global":{"features_MedianFuzzyHist":0.0,"features_AverageFuzzyHistNormalized":0.0,"features_AverageFuzzyHist":0.0},"local":{},"value":null},{"segment_id":"v_05981_10","global":{"features_MedianFuzzyHist":0.0,"features_AverageFuzzyHist":0.0},"local":{"features_AverageColorRaster":0.882421875},"value":0.110302734375},{"segment_id":"v_02682_184","global":{"features_MedianFuzzyHist":0.0,"features_AverageFuzzyHistNormalized":0.0},"local":{"features_AverageColorRaster":0.776953125},"value":0.097119140625}]}