{"queryId":"245c7a54-0104-47c5-9c07-a7373980d806","formattedDate":"05-11-2021 12:22:14","segments":[{"segment_id":"v_02635_10","global":{"features_MedianFuzzyHist":0.0,"features_AverageFuzzyHistNormalized":0.0},"local":{"features_AverageColorRaster":0.71015625},"value":0.08876953125},{"segment_id":"v_02635_11","global":{"features_MedianFuzzyHist":0.0,"features_AverageFuzzyHistNormalized":0.0,"features_MedianColor":0.2338071862045599},"local":{},"value":0.03438340973596469},{"segment_id":"v_02635_8","global":{"features_MedianFuzzyHist":0.0,"features_AverageFuzzyHistNormalized":0.0,"features_MedianColor":0.2338071862045599},"local":{},"value":0.03438340973596469},{"segment_id":"v_02635_9","global":{"features_MedianFuzzyHist":0.0,"features_AverageFuzzyHistNormalized":0.0,"features_MedianColor":0.2338071862045599},"local":{},"value":0.03438340973596469},{"segment_id":"v_02635_6","global":{"features_MedianFuzzyHist":0.0,"features_AverageFuzzyHistNormalized":0.0,"features_MedianColor":0.2338071862045599},"local":{},"value":0.03438340973596469},{"segment_id":"v_02635_7","global":{"features_MedianFuzzyHist":0.0,"features_AverageFuzzyHistNormalized":0.0,"features_MedianColor":0.2338071862045599},"local":{},"value":0.03438340973596469},{"segment_id":"v_02635_5","global":{"features_MedianFuzzyHist":0.0,"features_AverageFuzzyHistNormalized":0.0},"local":{},"value":null},{"segment_id":"v_02635_4","global":{"features_MedianFuzzyHist":0.0,"features_AverageFuzzyHistNormalized":0.0,"features_MedianColor":0.2640677004444355},"local":{},"value":0.03883348535947581},{"segment_id":"v_02632_44","global":{"features_MedianFuzzyHist":0.0,"features_AverageFuzzyHistNormalized":0.0},"local":{},"value":null},{"segment_id":"v_02635_3","global":{"features_MedianFuzzyHist":0.0,"features_AverageFuzzyHistNormalized":0.0},"local":{},"value":null},{"segment_id":"v_02635_2","global":{"features_MedianFuzzyHist":0.0,"features_AverageFuzzyHistNormalized":0.0,"features_MedianColor":0.2338071862045599},"local":{},"value":0.03438340973596469},{"segment_id":"v_02635_1","global":{"features_MedianFuzzyHist":0.0,"features_AverageFuzzyHistNormalized":0.0},"local":{"features_AverageColorGrid8":0.6003942013960502},"value":0.07504927517450627},{"segment_id":"v_02632_47","global":{"features_MedianFuzzyHist":0.0,"features_AverageFuzzyHistNormalized":0.0},"local":{"features_AverageColorGrid8":0.6003942013960502},"value":0.07504927517450627},{"segment_id":"v_02632_46","global":{"features_MedianFuzzyHist":0.0,"features_AverageFuzzyHistNormalized":0.0},"local":{},"value":null},{"segment_id":"v_02632_45","global":{"features_MedianFuzzyHist":0.0,"features_AverageFuzzyHistNormalized":0.0},"local":{},"value":null},{"segment_id":"v_02632_41","global":{"features_MedianFuzzyHist":0.0,"features_AverageFuzzyHistNormalized":0.0},"local":{},"value":null},{"segment_id":"v_02632_43","global":{"features_MedianFuzzyHist":0.0,"features_AverageFuzzyHistNormalized":0.0},"local":{},"value":null},{"segment_id":"v_02632_42","global":{"features_MedianFuzzyHist":0.0,"features_AverageFuzzyHistNormalized":0.0},"local":{},"value":null},{"segment_id":"v_02632_40","global":{"features_MedianFuzzyHist":0.0,"features_AverageFuzzyHistNormalized":0.0},"local":{"features_AverageColorRaster":0.5765625},"value":0.0720703125},{"segment_id":"v_02632_39","global":{"features_MedianFuzzyHist":0.0,"features_AverageFuzzyHistNormalized":0.0},"local":{"features_AverageColorRaster":0.6046875},"value":0.0755859375},{"segment_id":"v_02632_38","global":{"features_MedianFuzzyHist":0.0,"features_AverageFuzzyHistNormalized":0.0},"local":{"features_AverageColorRaster":0.615234375},"value":0.076904296875},{"segment_id":"v_02632_37","global":{"features_MedianFuzzyHist":0.0,"features_AverageFuzzyHistNormalized":0.0},"local":{"features_AverageColorRaster":1.1460937500000001},"value":0.14326171875000002},{"segment_id":"v_02632_36","global":{"features_MedianFuzzyHist":0.0,"features_AverageFuzzyHistNormalized":0.0},"local":{"features_AverageColorRaster":0.815625},"value":0.101953125},{"segment_id":"v_02632_35","global":{"features_MedianFuzzyHist":0.0,"features_AverageFuzzyHistNormalized":0.0},"local":{"features_AverageColorRaster":0.85078125},"value":0.10634765625},{"segment_id":"v_02632_34","global":{"features_MedianFuzzyHist":0.0,"features_AverageFuzzyHistNormalized":0.0},"local":{"features_AverageColorRaster":0.703125},"value":0.087890625},{"segment_id":"v_02632_33","global":{"features_MedianFuzzyHist":0.0,"features_AverageFuzzyHistNormalized":0.0},"local":{"features_AverageColorRaster":0.759375},"value":0.094921875},{"segment_id":"v_02632_32","global":{"features_MedianFuzzyHist":0.0,"features_AverageFuzzyHistNormalized":0.0},"local":{"features_AverageColorRaster":0.657421875},"value":0.082177734375},{"segment_id":"v_02632_31","global":{"features_MedianFuzzyHist":0.0,"features_AverageFuzzyHistNormalized":0.0},"local":{"features_AverageColorRaster":0.42890625},"value":0.05361328125},{"segment_id":"v_02632_30","global":{"features_MedianFuzzyHist":0.0,"features_AverageFuzzyHistNormalized":0.0},"local":{},"value":null},{"segment_id":"v_02632_29","global":{"features_MedianFuzzyHist":0.0,"features_AverageFuzzyHistNormalized":0.0},"local":{},"value":null},{"segment_id":"v_02632_28","global":{"features_MedianFuzzyHist":0.0,"features_AverageFuzzyHistNormalized":0.0},"local":{"features_AverageColorRaster":0.4921875},"value":0.0615234375},{"segment_id":"v_02632_27","global":{"features_MedianFuzzyHist":0.0,"features_AverageFuzzyHistNormalized":0.0},"local":{"features_AverageColorRaster":0.622265625},"value":0.077783203125},{"segment_id":"v_02632_26","global":{"features_MedianFuzzyHist":0.0,"features_AverageFuzzyHistNormalized":0.0},"local":{"features_AverageColorRaster":0.5027343750000001},"value":0.06284179687500001},{"segment_id":"v_02632_17","global":{"features_MedianFuzzyHist":0.0,"features_AverageFuzzyHistNormalized":0.0},"local":{"features_AverageColorRaster":0.544921875},"value":0.068115234375},{"segment_id":"v_02632_25","global":{"features_MedianFuzzyHist":0.0,"features_AverageFuzzyHistNormalized":0.0},"local":{"features_AverageColorRaster":0.6890625},"value":0.0861328125},{"segment_id":"v_02632_24","global":{"features_MedianFuzzyHist":0.0,"features_AverageFuzzyHistNormalized":0.0},"local":{},"value":null},{"segment_id":"v_02632_23","global":{"features_MedianFuzzyHist":0.0,"features_AverageFuzzyHistNormalized":0.0},"local":{"features_AverageColorRaster":0.41835937500000003},"value":0.052294921875000004},{"segment_id":"v_02632_22","global":{"features_MedianFuzzyHist":0.0,"features_AverageFuzzyHistNormalized":0.0},"local":{"features_AverageColorRaster":1.096875},"value":0.137109375},{"segment_id":"v_02632_21","global":{"features_MedianFuzzyHist":0.0,"features_AverageFuzzyHistNormalized":0.0},"local":{"features_AverageColorRaster":0.8015625000000001},"value":0.10019531250000001},{"segment_id":"v_02632_20","global":{"features_MedianFuzzyHist":0.0,"features_AverageFuzzyHistNormalized":0.0},"local":{"features_AverageColorRaster":1.29375},"value":0.16171875},{"segment_id":"v_02632_19","global":{"features_MedianFuzzyHist":0.0,"features_AverageFuzzyHistNormalized":0.0},"local":{"features_AverageColorRaster":0.7875},"value":0.0984375},{"segment_id":"v_02632_18","global":{"features_MedianFuzzyHist":0.0,"features_AverageFuzzyHistNormalized":0.0},"local":{"features_AverageColorRaster":0.826171875},"value":0.103271484375},{"segment_id":"v_02632_16","global":{"features_MedianFuzzyHist":0.0,"features_AverageFuzzyHistNormalized":0.0},"local":{},"value":null},{"segment_id":"v_02632_15","global":{"features_MedianFuzzyHist":0.0,"features_AverageFuzzyHistNormalized":0.0},"local":{"features_AverageColorRaster":0.566015625},"value":0.070751953125},{"segment_id":"v_02632_13","global":{"features_MedianFuzzyHist":0.0,"features_AverageFuzzyHistNormalized":0.0},"local":{},"value":null},{"segment_id":"v_02632_14","global":{"features_MedianFuzzyHist":0.0,"features_AverageFuzzyHistNormalized":0.0},"local":{},"value":null},{"segment_id":"v_02632_12","global":{"features_MedianFuzzyHist":0.0,"features_AverageFuzzyHistNormalized":0.0},"local":{},"value":null},{"segment_id":"v_02632_11","global":{"features_MedianFuzzyHist":0.0,"features_AverageFuzzyHistNormalized":0.0},"local":{"features_AverageColorRaster":0.566015625},"value":0.070751953125},{"segment_id":"v_02632_10","global":{"features_MedianFuzzyHist":0.0,"features_AverageFuzzyHistNormalized":0.0},"local":{"features_AverageColorRaster":0.59765625},"value":0.07470703125},{"segment_id":"v_02632_6","global":{"features_MedianFuzzyHist":0.0,"features_AverageFuzzyHistNormalized":0.0},"local":{},"value":null}]}